{
  "2026-06-01-00": {
    "hour": "2026-06-01-00",
    "generated_at": "2026-06-01T00:09:29.163Z",
    "total_logs_in_hour": 0,
    "unique_users": 0,
    "actions_summary": {},
    "device_summary": {}
  },
  "2026-06-01-05": {
    "hour": "2026-06-01-05",
    "generated_at": "2026-06-01T05:57:59.115Z",
    "total_logs_in_hour": 0,
    "unique_users": 0,
    "actions_summary": {},
    "device_summary": {}
  },
  "2026-06-01-11": {
    "hour": "2026-06-01-11",
    "generated_at": "2026-06-01T11:41:38.463Z",
    "total_logs_in_hour": 0,
    "unique_users": 0,
    "actions_summary": {},
    "device_summary": {}
  }
}