{
  "2026-02-14-01": {
    "hour": "2026-02-14-01",
    "generated_at": "2026-02-14T01:45:32.428Z",
    "total_logs_in_hour": 0,
    "unique_users": 0,
    "actions_summary": {},
    "device_summary": {}
  },
  "2026-02-14-04": {
    "hour": "2026-02-14-04",
    "generated_at": "2026-02-14T04:07:07.643Z",
    "total_logs_in_hour": 0,
    "unique_users": 0,
    "actions_summary": {},
    "device_summary": {}
  },
  "2026-02-14-05": {
    "hour": "2026-02-14-05",
    "generated_at": "2026-02-14T05:40:46.524Z",
    "total_logs_in_hour": 0,
    "unique_users": 0,
    "actions_summary": {},
    "device_summary": {}
  },
  "2026-02-14-06": {
    "hour": "2026-02-14-06",
    "generated_at": "2026-02-14T06:39:16.981Z",
    "total_logs_in_hour": 0,
    "unique_users": 0,
    "actions_summary": {},
    "device_summary": {}
  },
  "2026-02-14-07": {
    "hour": "2026-02-14-07",
    "generated_at": "2026-02-14T07:31:31.256Z",
    "total_logs_in_hour": 0,
    "unique_users": 0,
    "actions_summary": {},
    "device_summary": {}
  },
  "2026-02-14-08": {
    "hour": "2026-02-14-08",
    "generated_at": "2026-02-14T08:27:01.947Z",
    "total_logs_in_hour": 0,
    "unique_users": 0,
    "actions_summary": {},
    "device_summary": {}
  }
}