{
  "2026-02-19-01": {
    "hour": "2026-02-19-01",
    "generated_at": "2026-02-19T01:51:52.103Z",
    "total_logs_in_hour": 0,
    "unique_users": 0,
    "actions_summary": {},
    "device_summary": {}
  },
  "2026-02-19-04": {
    "hour": "2026-02-19-04",
    "generated_at": "2026-02-19T04:17:01.916Z",
    "total_logs_in_hour": 0,
    "unique_users": 0,
    "actions_summary": {},
    "device_summary": {}
  },
  "2026-02-19-05": {
    "hour": "2026-02-19-05",
    "generated_at": "2026-02-19T05:56:00.085Z",
    "total_logs_in_hour": 0,
    "unique_users": 0,
    "actions_summary": {},
    "device_summary": {}
  },
  "2026-02-19-06": {
    "hour": "2026-02-19-06",
    "generated_at": "2026-02-19T06:58:30.013Z",
    "total_logs_in_hour": 0,
    "unique_users": 0,
    "actions_summary": {},
    "device_summary": {}
  }
}