{
  "2026-03-19-01": {
    "hour": "2026-03-19-01",
    "generated_at": "2026-03-19T01:54:30.673Z",
    "total_logs_in_hour": 0,
    "unique_users": 0,
    "actions_summary": {},
    "device_summary": {}
  },
  "2026-03-19-04": {
    "hour": "2026-03-19-04",
    "generated_at": "2026-03-19T04:21:19.389Z",
    "total_logs_in_hour": 0,
    "unique_users": 0,
    "actions_summary": {},
    "device_summary": {}
  },
  "2026-03-19-05": {
    "hour": "2026-03-19-05",
    "generated_at": "2026-03-19T05:55:16.836Z",
    "total_logs_in_hour": 0,
    "unique_users": 0,
    "actions_summary": {},
    "device_summary": {}
  },
  "2026-03-19-06": {
    "hour": "2026-03-19-06",
    "generated_at": "2026-03-19T06:53:52.082Z",
    "total_logs_in_hour": 0,
    "unique_users": 0,
    "actions_summary": {},
    "device_summary": {}
  },
  "2026-03-19-07": {
    "hour": "2026-03-19-07",
    "generated_at": "2026-03-19T07:44:00.780Z",
    "total_logs_in_hour": 0,
    "unique_users": 0,
    "actions_summary": {},
    "device_summary": {}
  },
  "2026-03-19-08": {
    "hour": "2026-03-19-08",
    "generated_at": "2026-03-19T08:37:22.946Z",
    "total_logs_in_hour": 0,
    "unique_users": 0,
    "actions_summary": {},
    "device_summary": {}
  },
  "2026-03-19-09": {
    "hour": "2026-03-19-09",
    "generated_at": "2026-03-19T09:38:53.769Z",
    "total_logs_in_hour": 0,
    "unique_users": 0,
    "actions_summary": {},
    "device_summary": {}
  },
  "2026-03-19-10": {
    "hour": "2026-03-19-10",
    "generated_at": "2026-03-19T10:35:49.840Z",
    "total_logs_in_hour": 0,
    "unique_users": 0,
    "actions_summary": {},
    "device_summary": {}
  },
  "2026-03-19-11": {
    "hour": "2026-03-19-11",
    "generated_at": "2026-03-19T11:32:35.181Z",
    "total_logs_in_hour": 0,
    "unique_users": 0,
    "actions_summary": {},
    "device_summary": {}
  },
  "2026-03-19-12": {
    "hour": "2026-03-19-12",
    "generated_at": "2026-03-19T12:55:51.894Z",
    "total_logs_in_hour": 0,
    "unique_users": 0,
    "actions_summary": {},
    "device_summary": {}
  },
  "2026-03-19-14": {
    "hour": "2026-03-19-14",
    "generated_at": "2026-03-19T14:06:52.971Z",
    "total_logs_in_hour": 0,
    "unique_users": 0,
    "actions_summary": {},
    "device_summary": {}
  },
  "2026-03-19-15": {
    "hour": "2026-03-19-15",
    "generated_at": "2026-03-19T15:51:09.305Z",
    "total_logs_in_hour": 0,
    "unique_users": 0,
    "actions_summary": {},
    "device_summary": {}
  },
  "2026-03-19-16": {
    "hour": "2026-03-19-16",
    "generated_at": "2026-03-19T16:54:10.987Z",
    "total_logs_in_hour": 0,
    "unique_users": 0,
    "actions_summary": {},
    "device_summary": {}
  },
  "2026-03-19-17": {
    "hour": "2026-03-19-17",
    "generated_at": "2026-03-19T17:51:08.596Z",
    "total_logs_in_hour": 0,
    "unique_users": 0,
    "actions_summary": {},
    "device_summary": {}
  },
  "2026-03-19-18": {
    "hour": "2026-03-19-18",
    "generated_at": "2026-03-19T18:52:47.626Z",
    "total_logs_in_hour": 0,
    "unique_users": 0,
    "actions_summary": {},
    "device_summary": {}
  }
}